niva_api_client/__init__.py
niva_api_client/api_client.py
niva_api_client/domain/__init__.py
niva_api_client/domain/access_token.py
niva_api_client/domain/app.py
niva_api_client/domain/niva_user.py
niva_api_client/environments.py
niva_api_client/tests/test_url_utils.py
niva_api_client/tests/testutils.py
niva_api_client/url_utils.py
niva_api_client-0.1.2.dist-info/LICENSE
niva_api_client-0.1.2.dist-info/WHEEL
niva_api_client-0.1.2.dist-info/METADATA
niva_api_client-0.1.2.dist-info/RECORD
